evapotranspiration/__init__.py
evapotranspiration/penman_monteith_daily.py
evapotranspiration-0.0.4.dist-info/LICENSE.txt
evapotranspiration-0.0.4.dist-info/METADATA
evapotranspiration-0.0.4.dist-info/WHEEL
evapotranspiration-0.0.4.dist-info/top_level.txt
evapotranspiration-0.0.4.dist-info/RECORD
