Metadata-Version: 2.1
Name: evapotranspiration
Version: 0.0.4
Summary: evapotranspiration
Home-page: https://github.com/JRoehrig/evapotranspiration
Author: Jackson Roehrig & Maria Paula Lorza Villegas
Author-email: Jackson.Roehrig@th-koeln.de
License: MIT
Download-URL: https://github.com/JRoehrig/evapotranspiration
Platform: UNKNOWN
Classifier: Development Status :: 4 - Beta
Classifier: Environment :: Console
Classifier: Intended Audience :: Science/Research
Classifier: License :: OSI Approved :: MIT License
Classifier: Natural Language :: English
Classifier: Operating System :: OS Independent
Classifier: Programming Language :: Python :: 3 :: Only
Classifier: Topic :: Scientific/Engineering :: Hydrology
Requires-Dist: pandas
